{"cameraMode":{"drawMode":0,"name":"Shaded","section":"Shading Mode"},"sceneLighting":true,"audioPlay":false,"sceneViewState":{"m_AlwaysRefresh":false,"showFog":true,"showSkybox":true,"showFlares":true,"showImageEffects":true,"showParticleSystems":true,"showVisualEffectGraphs":true,"m_FxEnabled":true},"in2DMode":false,"pivot":{"x":-101.1278076171875,"y":17.28907585144043,"z":1.8804861307144166},"rotation":{"x":0.06824325770139694,"y":0.4803833067417145,"z":-0.03705074265599251,"w":0.8740072846412659},"size":9.042153358459473,"orthographic":false}